Metadata-Version: 2.2
Name: varfish_cli
Version: 0.7.0
Summary: Command line interface client for VarFish Server.
Home-page: https://github.com/bihealth/varfish-cli
Author: Manuel Holtgrewe
Author-email: manuel.holtgrewe@bihealth.de
License: MIT license
Keywords: varfish_cli
Classifier: Development Status :: 4 - Beta
Classifier: Intended Audience :: Developers
Classifier: License :: OSI Approved :: MIT License
Classifier: Natural Language :: English
Classifier: Topic :: Scientific/Engineering :: Bio-Informatics
Classifier: Programming Language :: Python :: 3
Classifier: Programming Language :: Python :: 3.10
Classifier: Programming Language :: Python :: 3.11
Classifier: Programming Language :: Python :: 3.12
License-File: LICENSE
License-File: AUTHORS.rst
Requires-Dist: python-dateutil<3.0,>=2.8.1
Requires-Dist: pydantic<3,>=2
Requires-Dist: toml<0.11,>=0.10.2
Requires-Dist: typer<0.13,>=0.9
Requires-Dist: jsonschema<4.24,>=4.4
Requires-Dist: logzero<2.0,>=1.7.0
Requires-Dist: simplejson<4.0,>=3.17.2
Requires-Dist: requests<3.0,>=2.25.1
Requires-Dist: tqdm<5.0,>=4.61.1
Requires-Dist: tabulate<0.10,>=0.8.9
Requires-Dist: polyleven<0.9,>=0.8
Requires-Dist: jsonschema<4.24,>=4.4.0
Requires-Dist: typeguard<5.0,>=2.13.3
Dynamic: author
Dynamic: author-email
Dynamic: classifier
Dynamic: description
Dynamic: description-content-type
Dynamic: home-page
Dynamic: keywords
Dynamic: license
Dynamic: requires-dist
Dynamic: summary
